{
  "project_info": {
    "project_number": "814407182169",
    "project_id": "ammaplant-b81f2",
    "storage_bucket": "ammaplant-b81f2.appspot.com"
  },
  "client": [
    {
      "client_info": {
        "mobilesdk_app_id": "1:814407182169:android:3cc2cfa2a83ffa94364e48",
        "android_client_info": {
          "package_name": "com.amma_plant"
        }
      },
      "oauth_client": [
        {
          "client_id": "814407182169-bbqj8fefu61vopagh2l37a6gj7rnab95.apps.googleusercontent.com",
          "client_type": 1,
          "android_info": {
            "package_name": "com.amma_plant",
            "certificate_hash": "b5675c839851f277ac017f95ed3c2d8f21f04831"
          }
        },
        {
          "client_id": "814407182169-g7s1gqki8sgpi7fdqtqkjm6knb3epdei.apps.googleusercontent.com",
          "client_type": 1,
          "android_info": {
            "package_name": "com.amma_plant",
            "certificate_hash": "5e8f16062ea3cd2c4a0d547876baa6f38cabf625"
          }
        },
        {
          "client_id": "814407182169-57gk9a8i2plth612gk3ont22fbt3emmu.apps.googleusercontent.com",
          "client_type": 3
        }
      ],
      "api_key": [
        {
          "current_key": "AIzaSyDVjyIby0MahYMgwVmCzN4AOtrfXKDnIns"
        }
      ],
      "services": {
        "appinvite_service": {
          "other_platform_oauth_client": [
            {
              "client_id": "814407182169-57gk9a8i2plth612gk3ont22fbt3emmu.apps.googleusercontent.com",
              "client_type": 3
            }
          ]
        }
      }
    }
  ],
  "configuration_version": "1"
}